restackio/ai/__init__.py
restackio/ai/event.py
restackio/ai/function.py
restackio/ai/memory.py
restackio/ai/observability.py
restackio/ai/playground/workflow.py
restackio/ai/py.typed
restackio/ai/restack.py
restackio/ai/utils.py
restackio/ai/workflow.py
restackio_ai-0.0.11.dist-info/METADATA
restackio_ai-0.0.11.dist-info/WHEEL
restackio_ai-0.0.11.dist-info/RECORD
