Metadata-Version: 2.1
Name: restackio.ai
Version: 0.0.11
Summary: Python Restack AI Core
Author: Restack Team
Author-email: service@restack.io
Requires-Python: >=3.8,<4.0
Classifier: Programming Language :: Python :: 3
Classifier: Programming Language :: Python :: 3.8
Classifier: Programming Language :: Python :: 3.9
Classifier: Programming Language :: Python :: 3.10
Classifier: Programming Language :: Python :: 3.11
Classifier: Programming Language :: Python :: 3.12
Requires-Dist: pydantic (==2.9.2)
Requires-Dist: python-dotenv (>=0.19.0,<0.20.0)
Requires-Dist: temporalio (==1.7.1)
